federated_core/__init__.py
federated_core/compatibility/__init__.py
federated_core/compatibility/algorithms.py
federated_core/compatibility/framework/__init__.py
federated_core/compatibility/framework/one_framework.py
federated_core/compatibility/framework/tensorflow.py
federated_core/compatibility/framework/torch.py
federated_core/engine/__init__.py
federated_core/engine/parallelism.py
federated_core/engine/sequence.py
federated_core/environment/__init__.py
federated_core/environment/dataset/__init__.py
federated_core/environment/dataset/spliter.py
federated_core/environment/dataset/policy/__init__.py
federated_core/environment/dataset/policy/label.py
federated_core/environment/dataset/policy/quantity.py
federated_core/environment/setting/__init__.py
federated_core/environment/setting/builder.py
federated_core/environment/topology/__init__.py
federated_core/environment/topology/generator.py
federated_core/environment/topology/type/__init__.py
federated_core/environment/topology/type/all_reduce.py
federated_core/environment/topology/type/gossip.py
federated_core/environment/topology/type/parameter_server.py
federated_core/federation/__init__.py
federated_core/federation/edge/__init__.py
federated_core/federation/edge/queuer.py
federated_core/federation/edge/tcper.py
federated_core/federation/vertex/__init__.py
federated_core/federation/vertex/host.py
federated_core/federation/vertex/primitives.py
federated_core/misc/__init__.py
federated_core/misc/analysis.py
federated_core/misc/enums.py
federated_core/misc/globalvar.py
federated_core/misc/tools.py
federatedcore/__init__.py
federatedcore/compatibility/__init__.py
federatedcore/compatibility/algorithms.py
federatedcore/compatibility/framework/__init__.py
federatedcore/compatibility/framework/one_framework.py
federatedcore/compatibility/framework/tensorflow.py
federatedcore/compatibility/framework/torch.py
federatedcore/engine/__init__.py
federatedcore/engine/parallelism.py
federatedcore/engine/sequence.py
federatedcore-0.0.2.dist-info/LICENSE
federatedcore-0.0.2.dist-info/METADATA
federatedcore-0.0.2.dist-info/WHEEL
federatedcore-0.0.2.dist-info/top_level.txt
federatedcore-0.0.2.dist-info/RECORD
