Metadata-Version: 2.1
Name: federatedcore
Version: 0.0.2
Summary: A research-oriented federal learning framework.
Home-page: https://github.com/songs18/FederatedCore
Author: songs18
Author-email: sounghaohao@gmail.com
License: MIT
Platform: all
License-File: LICENSE
Requires-Dist: decorator
Requires-Dist: networkx
Requires-Dist: numpy
